extractipedia/CheckDatabase.py
extractipedia/Extraction.py
extractipedia/__init__.py
extractipedia/utils.py
extractipedia-0.0.2.dist-info/LICENCE
extractipedia-0.0.2.dist-info/METADATA
extractipedia-0.0.2.dist-info/WHEEL
extractipedia-0.0.2.dist-info/top_level.txt
extractipedia-0.0.2.dist-info/RECORD
