Metadata-Version: 2.1
Name: extractipedia
Version: 0.0.2
Summary: A simple tool that extracts plain text Wikipedia Pages to SQLite database.
Home-page: https://github.com/sharkcommits/extractipedia
Author: sharkcommits
Author-email: sharkcommits@protonmail.com
License: GPLv3
Classifier: License :: OSI Approved :: GNU General Public License v3 (GPLv3)
Classifier: Programming Language :: Python :: 3.10
Classifier: Operating System :: OS Independent
Requires-Python: >=3.10
License-File: LICENCE
Provides-Extra: dev
Requires-Dist: pytest (>=7.0) ; extra == 'dev'
Requires-Dist: twine (>=4.0.2) ; extra == 'dev'
